setup.py
bknews/__init__.py
bknews/parser.py
bknews.egg-info/PKG-INFO
bknews.egg-info/SOURCES.txt
bknews.egg-info/dependency_links.txt
bknews.egg-info/not-zip-safe
bknews.egg-info/top_level.txt