Metadata-Version: 1.0
Name: bknews
Version: 0.1
Summary: Tools for bknews
Home-page: http://sangnd.com
Author: heroandtn3
Author-email: heroandtn3@gmail.com
License: GPLv3
Platform: UNKNOWN
